pvt_model/__init__.py
pvt_model/__main__.py
pvt_model/__utils__.py
pvt_model/argparser.py
pvt_model/analysis/__init__.py
pvt_model/analysis/__utils__.py
pvt_model/analysis/analysis.py
pvt_model/analysis/five_param_fitting.py
pvt_model/analysis/five_param_fitting_chunked.py
pvt_model/analysis/four_param_fitting.py
pvt_model/analysis/glazing_analysis.py
pvt_model/analysis/machine_learning_fit.py
pvt_model/analysis/mass_flow_rate_analysis.py
pvt_model/analysis/thesis_analysis.py
pvt_model/analysis/three_param_fitting.py
pvt_model/analysis/two_param_fitting.py
pvt_model/analysis/validation_analysis.py
pvt_model/enforcement/__init__.py
pvt_model/enforcement/mypy_enforcement.py
pvt_model/enforcement/pylint_enforcement.py
pvt_model/pvt_system/__init__.py
pvt_model/pvt_system/__main__.py
pvt_model/pvt_system/__utils__.py
pvt_model/pvt_system/constants.py
pvt_model/pvt_system/convergent_solver.py
pvt_model/pvt_system/efficiency.py
pvt_model/pvt_system/exchanger.py
pvt_model/pvt_system/index_handler.py
pvt_model/pvt_system/load.py
pvt_model/pvt_system/mains_power.py
pvt_model/pvt_system/physics_utils.py
pvt_model/pvt_system/pipe.py
pvt_model/pvt_system/process_pvt_system_data.py
pvt_model/pvt_system/pump.py
pvt_model/pvt_system/tank.py
pvt_model/pvt_system/weather.py
pvt_model/pvt_system/matrix/__init__.py
pvt_model/pvt_system/matrix/absorber.py
pvt_model/pvt_system/matrix/continuity.py
pvt_model/pvt_system/matrix/glass.py
pvt_model/pvt_system/matrix/htf.py
pvt_model/pvt_system/matrix/matrix.py
pvt_model/pvt_system/matrix/pipe.py
pvt_model/pvt_system/matrix/pv.py
pvt_model/pvt_system/matrix/tank.py
pvt_model/pvt_system/matrix/upper_glass.py
pvt_model/pvt_system/pvt_collector/__init__.py
pvt_model/pvt_system/pvt_collector/__utils__.py
pvt_model/pvt_system/pvt_collector/absorber.py
pvt_model/pvt_system/pvt_collector/adhesive.py
pvt_model/pvt_system/pvt_collector/bond.py
pvt_model/pvt_system/pvt_collector/element.py
pvt_model/pvt_system/pvt_collector/eva.py
heatpanel-1.1.4.dist-info/LICENSE
heatpanel-1.1.4.dist-info/METADATA
heatpanel-1.1.4.dist-info/WHEEL
heatpanel-1.1.4.dist-info/entry_points.txt
heatpanel-1.1.4.dist-info/top_level.txt
heatpanel-1.1.4.dist-info/RECORD
