Metadata-Version: 2.1
Name: heatpanel
Version: 1.1.4
Summary: Hybrid Electric and Heat Panel Model
Home-page: https://github.com/BenWinchester/PVTModel
Author: Ben Winchester
Author-email: benedict.winchester@gmail.com
Project-URL: Bug Tracker, https://github.com/BenWinchester/PVTModel/issues
Classifier: Programming Language :: Python :: 3.7
Classifier: License :: OSI Approved :: MIT License
Classifier: Operating System :: OS Independent
Requires-Python: >=3.7
License-File: LICENSE
Requires-Dist: black>=20.8b1
Requires-Dist: colorclass>=2.2.0
Requires-Dist: data-science-types>=0.2.23
Requires-Dist: dtreeviz>=1.3.1
Requires-Dist: entrypoints>=0.3
Requires-Dist: importlib-metadata>=3.4.0
Requires-Dist: iniconfig>=1.1.1
Requires-Dist: isort>=5.7.0
Requires-Dist: jedi>=0.18.0
Requires-Dist: keyring>=17.1.1
Requires-Dist: kiwisolver>=1.3.1
Requires-Dist: matplotlib>=3.3.4
Requires-Dist: mypy>=0.812
Requires-Dist: numpy>=1.20.1
Requires-Dist: packaging>=20.9
Requires-Dist: pandas>=1.2.3
Requires-Dist: pylint>=2.7.2
Requires-Dist: pysolar>=0.9
Requires-Dist: pytest>=6.2.2
Requires-Dist: python-dateutil>=2.8.1
Requires-Dist: pytz>=2021.1
Requires-Dist: PyYAML>=5.4.1
Requires-Dist: regex>=2021.3.17
Requires-Dist: scipy>=1.6.1
Requires-Dist: scikit-learn>=0.0
Requires-Dist: tqdm>=4.59.0
Requires-Dist: types-python-dateutil>=0.1.2
Requires-Dist: types-pytz>=0.1.0
Requires-Dist: types-PyYaml>=0.1.6
Requires-Dist: yamllint>=1.15.0
